requirements.txt
pyensembl/__init__.py
pyensembl/common.py
pyensembl/database.py
pyensembl/download_cache.py
pyensembl/ensembl_release.py
pyensembl/ensembl_url_templates.py
pyensembl/ensembl_versions.py
pyensembl/exon.py
pyensembl/fasta.py
pyensembl/gene.py
pyensembl/genome.py
pyensembl/locus.py
pyensembl/locus_with_genome.py
pyensembl/logging.conf
pyensembl/normalization.py
pyensembl/reference_name.py
pyensembl/search.py
pyensembl/sequence_data.py
pyensembl/shell.py
pyensembl/species.py
pyensembl/transcript.py
pyensembl/version.py
pyensembl-2.3.12.dist-info/LICENSE
pyensembl-2.3.12.dist-info/METADATA
pyensembl-2.3.12.dist-info/WHEEL
pyensembl-2.3.12.dist-info/entry_points.txt
pyensembl-2.3.12.dist-info/top_level.txt
pyensembl-2.3.12.dist-info/RECORD
