Metadata-Version: 2.1
Name: pyensembl
Version: 2.3.12
Summary: Python interface to Ensembl reference genome metadata
Home-page: https://github.com/openvax/pyensembl
Author: Alex Rubinsteyn
Author-email: alex.rubinsteyn@unc.edu
License: http://www.apache.org/licenses/LICENSE-2.0.html
Classifier: Development Status :: 4 - Beta
Classifier: Environment :: Console
Classifier: Operating System :: OS Independent
Classifier: Intended Audience :: Science/Research
Classifier: License :: OSI Approved :: Apache Software License
Classifier: Programming Language :: Python
Classifier: Topic :: Scientific/Engineering :: Bio-Informatics
License-File: LICENSE
Requires-Dist: typechecks <1.0.0,>=0.0.2
Requires-Dist: datacache <2.0.0,>=1.4.0
Requires-Dist: memoized-property >=1.0.2
Requires-Dist: tinytimer <1.0.0,>=0.0.0
Requires-Dist: gtfparse <3.0.0,>=2.5.0
Requires-Dist: serializable <1.0.0,>=0.2.1
Requires-Dist: pylint <3.0.0,>=2.17.2
